<?xml version="1.0" encoding="UTF-8"?>
<export version="D">
  <design>
    <source>/home/alkann/Ham/Projets/VFO-DO/vfo-do.sch</source>
    <date>lun. 07 juin 2021 21:45:24</date>
    <tool>Eeschema 5.1.5+dfsg1-2build2</tool>
    <sheet number="1" name="/" tstamps="/">
      <title_block>
        <title/>
        <company/>
        <rev/>
        <date/>
        <source>vfo-do.sch</source>
        <comment number="1" value=""/>
        <comment number="2" value=""/>
        <comment number="3" value=""/>
        <comment number="4" value=""/>
      </title_block>
    </sheet>
  </design>
  <components>
    <comp ref="U4">
      <value>Arduino_Nano</value>
      <footprint>arduino:arduino_nano</footprint>
      <libsource lib="vfo-do-rescue" part="Arduino_Nano" description=""/>
      <sheetpath names="/" tstamps="/"/>
      <tstamp>57138B7B</tstamp>
    </comp>
    <comp ref="P5">
      <value>GPS</value>
      <footprint>Connectors_Molex:Molex_KK-6410-04_04x2.54mm_Straight</footprint>
      <libsource lib="vfo-do-rescue" part="CONN_01X04" description=""/>
      <sheetpath names="/" tstamps="/"/>
      <tstamp>57139983</tstamp>
    </comp>
    <comp ref="P4">
      <value>Encoder</value>
      <footprint>Connectors_Molex:Molex_KK-6410-04_04x2.54mm_Straight</footprint>
      <libsource lib="vfo-do-rescue" part="CONN_01X04" description=""/>
      <sheetpath names="/" tstamps="/"/>
      <tstamp>57139B2F</tstamp>
    </comp>
    <comp ref="P1">
      <value>12V in</value>
      <footprint>Connectors_Molex:Molex_KK-6410-02_02x2.54mm_Straight</footprint>
      <libsource lib="vfo-do-rescue" part="CONN_01X02" description=""/>
      <sheetpath names="/" tstamps="/"/>
      <tstamp>5713C7D4</tstamp>
    </comp>
    <comp ref="D1">
      <value>D_Schottky</value>
      <footprint>Diodes_SMD:SMB_Handsoldering</footprint>
      <libsource lib="vfo-do-rescue" part="D_Schottky" description=""/>
      <sheetpath names="/" tstamps="/"/>
      <tstamp>5713C927</tstamp>
    </comp>
    <comp ref="C1">
      <value>100n</value>
      <footprint>Capacitors_SMD:C_1206_HandSoldering</footprint>
      <libsource lib="vfo-do-rescue" part="C" description=""/>
      <sheetpath names="/" tstamps="/"/>
      <tstamp>5713E012</tstamp>
    </comp>
    <comp ref="C2">
      <value>100n</value>
      <footprint>Capacitors_SMD:C_1206_HandSoldering</footprint>
      <libsource lib="vfo-do-rescue" part="C" description=""/>
      <sheetpath names="/" tstamps="/"/>
      <tstamp>5713E09B</tstamp>
    </comp>
    <comp ref="C6">
      <value>100n</value>
      <footprint>Capacitors_SMD:C_1206_HandSoldering</footprint>
      <libsource lib="vfo-do-rescue" part="C" description=""/>
      <sheetpath names="/" tstamps="/"/>
      <tstamp>5713E0DE</tstamp>
    </comp>
    <comp ref="C5">
      <value>100n</value>
      <footprint>Capacitors_SMD:C_1206_HandSoldering</footprint>
      <libsource lib="vfo-do-rescue" part="C" description=""/>
      <sheetpath names="/" tstamps="/"/>
      <tstamp>5713E11D</tstamp>
    </comp>
    <comp ref="C3">
      <value>100n</value>
      <footprint>Capacitors_SMD:C_1206_HandSoldering</footprint>
      <libsource lib="vfo-do-rescue" part="C" description=""/>
      <sheetpath names="/" tstamps="/"/>
      <tstamp>5713E2A8</tstamp>
    </comp>
    <comp ref="C7">
      <value>100n</value>
      <footprint>Capacitors_SMD:C_1206_HandSoldering</footprint>
      <libsource lib="vfo-do-rescue" part="C" description=""/>
      <sheetpath names="/" tstamps="/"/>
      <tstamp>5713E3C1</tstamp>
    </comp>
    <comp ref="C4">
      <value>1500uF</value>
      <footprint>Capacitors_SMD:c_elec_6.3x7.7</footprint>
      <libsource lib="vfo-do-rescue" part="CP_Small" description=""/>
      <sheetpath names="/" tstamps="/"/>
      <tstamp>5713E47F</tstamp>
    </comp>
    <comp ref="C9">
      <value>100n</value>
      <footprint>Capacitors_SMD:C_1206_HandSoldering</footprint>
      <libsource lib="vfo-do-rescue" part="C" description=""/>
      <sheetpath names="/" tstamps="/"/>
      <tstamp>5718C6A0</tstamp>
    </comp>
    <comp ref="C10">
      <value>100n</value>
      <footprint>Capacitors_SMD:C_1206_HandSoldering</footprint>
      <libsource lib="vfo-do-rescue" part="C" description=""/>
      <sheetpath names="/" tstamps="/"/>
      <tstamp>5718DD22</tstamp>
    </comp>
    <comp ref="P7">
      <value>Band</value>
      <footprint>Connectors_Molex:Molex_KK-6410-02_02x2.54mm_Straight</footprint>
      <libsource lib="vfo-do-rescue" part="CONN_01X02" description=""/>
      <sheetpath names="/" tstamps="/"/>
      <tstamp>58FFA89F</tstamp>
    </comp>
    <comp ref="P8">
      <value>Reset</value>
      <footprint>Connectors_Molex:Molex_KK-6410-02_02x2.54mm_Straight</footprint>
      <libsource lib="vfo-do-rescue" part="CONN_01X02" description=""/>
      <sheetpath names="/" tstamps="/"/>
      <tstamp>58FFBAC8</tstamp>
    </comp>
    <comp ref="P6">
      <value>UP</value>
      <footprint>Connectors_Molex:Molex_KK-6410-02_02x2.54mm_Straight</footprint>
      <libsource lib="vfo-do-rescue" part="CONN_01X02" description=""/>
      <sheetpath names="/" tstamps="/"/>
      <tstamp>58FFD4FD</tstamp>
    </comp>
    <comp ref="P2">
      <value>DWN</value>
      <footprint>Connectors_Molex:Molex_KK-6410-02_02x2.54mm_Straight</footprint>
      <libsource lib="vfo-do-rescue" part="CONN_01X02" description=""/>
      <sheetpath names="/" tstamps="/"/>
      <tstamp>58FFD541</tstamp>
    </comp>
    <comp ref="U2">
      <value>LM7808_TO220</value>
      <footprint>Package_TO_SOT_THT:TO-220-3_Vertical</footprint>
      <datasheet>http://www.fairchildsemi.com/ds/LM/LM7805.pdf</datasheet>
      <libsource lib="Regulator_Linear" part="LM7808_TO220" description="Positive 1A 35V Linear Regulator, Fixed Output 8V, TO-220"/>
      <sheetpath names="/" tstamps="/"/>
      <tstamp>60BCC99B</tstamp>
    </comp>
    <comp ref="U6">
      <value>LM7805_TO220</value>
      <footprint>Package_TO_SOT_THT:TO-220-3_Vertical</footprint>
      <datasheet>http://www.fairchildsemi.com/ds/LM/LM7805.pdf</datasheet>
      <libsource lib="Regulator_Linear" part="LM7805_TO220" description="Positive 1A 35V Linear Regulator, Fixed Output 5V, TO-220"/>
      <sheetpath names="/" tstamps="/"/>
      <tstamp>60BE32ED</tstamp>
    </comp>
    <comp ref="U3">
      <value>LM7805_TO220</value>
      <footprint>Package_TO_SOT_THT:TO-220-3_Vertical</footprint>
      <datasheet>http://www.fairchildsemi.com/ds/LM/LM7805.pdf</datasheet>
      <libsource lib="Regulator_Linear" part="LM7805_TO220" description="Positive 1A 35V Linear Regulator, Fixed Output 5V, TO-220"/>
      <sheetpath names="/" tstamps="/"/>
      <tstamp>60BEE1D4</tstamp>
    </comp>
    <comp ref="U5">
      <value>LM7805_TO220</value>
      <footprint>Package_TO_SOT_THT:TO-220-3_Vertical</footprint>
      <datasheet>http://www.fairchildsemi.com/ds/LM/LM7805.pdf</datasheet>
      <libsource lib="Regulator_Linear" part="LM7805_TO220" description="Positive 1A 35V Linear Regulator, Fixed Output 5V, TO-220"/>
      <sheetpath names="/" tstamps="/"/>
      <tstamp>60BEF36D</tstamp>
    </comp>
    <comp ref="U1">
      <value>24AA02-OT</value>
      <footprint>Package_TO_SOT_SMD:SOT-23-5</footprint>
      <datasheet>http://ww1.microchip.com/downloads/en/DeviceDoc/21709J.pdf</datasheet>
      <libsource lib="Memory_EEPROM" part="24AA02-OT" description="I2C Serial EEPROM, 2Kb, SOT-23"/>
      <sheetpath names="/" tstamps="/"/>
      <tstamp>60C6D0A6</tstamp>
    </comp>
    <comp ref="P3">
      <value>Si5351</value>
      <footprint>Connectors_Molex:Molex_KK-6410-07_07x2.54mm_Straight</footprint>
      <libsource lib="vfo-do-rescue" part="CONN_01X07" description=""/>
      <sheetpath names="/" tstamps="/"/>
      <tstamp>571399D1</tstamp>
    </comp>
  </components>
  <libparts>
    <libpart lib="Memory_EEPROM" part="24AA02-OT">
      <description>I2C Serial EEPROM, 2Kb, SOT-23</description>
      <docs>http://ww1.microchip.com/downloads/en/DeviceDoc/21709J.pdf</docs>
      <footprints>
        <fp>SOT?23*</fp>
      </footprints>
      <fields>
        <field name="Reference">U</field>
        <field name="Value">24AA02-OT</field>
        <field name="Footprint">Package_TO_SOT_SMD:SOT-23-5</field>
      </fields>
      <pins>
        <pin num="1" name="SCL" type="input"/>
        <pin num="2" name="GND" type="power_in"/>
        <pin num="3" name="SDA" type="BiDi"/>
        <pin num="4" name="VCC" type="power_in"/>
        <pin num="5" name="NC" type="NotConnected"/>
      </pins>
    </libpart>
    <libpart lib="Regulator_Linear" part="LM7805_TO220">
      <aliases>
        <alias>LM7806_TO220</alias>
        <alias>LM7808_TO220</alias>
        <alias>LM7809_TO220</alias>
        <alias>LM7810_TO220</alias>
        <alias>LM7812_TO220</alias>
        <alias>LM7815_TO220</alias>
        <alias>LM7818_TO220</alias>
        <alias>LM7824_TO220</alias>
        <alias>LM78M05_TO220</alias>
        <alias>SPX2920U-3.3_TO220</alias>
        <alias>SPX2920U-5.0_TO220</alias>
        <alias>LF15_TO220</alias>
        <alias>LF18_TO220</alias>
        <alias>LF25_TO220</alias>
        <alias>LF33_TO220</alias>
        <alias>LF50_TO220</alias>
        <alias>LF60_TO220</alias>
        <alias>LF80_TO220</alias>
        <alias>LF85_TO220</alias>
        <alias>LF120_TO220</alias>
        <alias>LF47_TO220</alias>
        <alias>LF90_TO220</alias>
        <alias>LM341T-05_TO220</alias>
        <alias>LM341T-12_TO220</alias>
        <alias>LM341T-15_TO220</alias>
        <alias>LM2937xT</alias>
      </aliases>
      <description>Positive 1A 35V Linear Regulator, Fixed Output 5V, TO-220</description>
      <docs>http://www.fairchildsemi.com/ds/LM/LM7805.pdf</docs>
      <footprints>
        <fp>TO?220*</fp>
      </footprints>
      <fields>
        <field name="Reference">U</field>
        <field name="Value">LM7805_TO220</field>
        <field name="Footprint">Package_TO_SOT_THT:TO-220-3_Vertical</field>
      </fields>
      <pins>
        <pin num="1" name="VI" type="power_in"/>
        <pin num="2" name="GND" type="power_in"/>
        <pin num="3" name="VO" type="power_out"/>
      </pins>
    </libpart>
    <libpart lib="vfo-do-rescue" part="Arduino_Nano">
      <fields>
        <field name="Reference">U</field>
        <field name="Value">Arduino_Nano</field>
        <field name="Footprint">DIL30</field>
      </fields>
      <pins>
        <pin num="1" name="(led)(SCK)D13" type="input"/>
        <pin num="2" name="3V3" type="power_out"/>
        <pin num="3" name="Aref" type="input"/>
        <pin num="4" name="A0" type="BiDi"/>
        <pin num="5" name="A1" type="BiDi"/>
        <pin num="6" name="A2" type="BiDi"/>
        <pin num="7" name="A3" type="BiDi"/>
        <pin num="8" name="A4" type="BiDi"/>
        <pin num="9" name="A5" type="BiDi"/>
        <pin num="10" name="A6" type="BiDi"/>
        <pin num="11" name="A7" type="BiDi"/>
        <pin num="12" name="5V" type="power_out"/>
        <pin num="13" name="Reset" type="input"/>
        <pin num="14" name="GND" type="power_in"/>
        <pin num="15" name="Vin" type="power_in"/>
        <pin num="16" name="(TX)D1" type="BiDi"/>
        <pin num="17" name="(RX)D0" type="BiDi"/>
        <pin num="18" name="Reset" type="input"/>
        <pin num="19" name="GND" type="power_in"/>
        <pin num="20" name="(int2)D2" type="BiDi"/>
        <pin num="21" name="(int3)#D3" type="BiDi"/>
        <pin num="22" name="D4" type="BiDi"/>
        <pin num="23" name="#D5" type="BiDi"/>
        <pin num="24" name="#D6" type="BiDi"/>
        <pin num="25" name="D7" type="BiDi"/>
        <pin num="26" name="D8" type="BiDi"/>
        <pin num="27" name="#D9" type="BiDi"/>
        <pin num="28" name="(SS)#D10" type="BiDi"/>
        <pin num="29" name="(MOSI)#D11" type="BiDi"/>
        <pin num="30" name="(MISO)D12" type="BiDi"/>
      </pins>
    </libpart>
    <libpart lib="vfo-do-rescue" part="C">
      <footprints>
        <fp>C_*</fp>
      </footprints>
      <fields>
        <field name="Reference">C</field>
        <field name="Value">C</field>
      </fields>
      <pins>
        <pin num="1" name="~" type="passive"/>
        <pin num="2" name="~" type="passive"/>
      </pins>
    </libpart>
    <libpart lib="vfo-do-rescue" part="CONN_01X02">
      <footprints>
        <fp>Pin_Header_Straight_1X*</fp>
        <fp>Pin_Header_Angled_1X*</fp>
        <fp>Socket_Strip_Straight_1X*</fp>
        <fp>Socket_Strip_Angled_1X*</fp>
      </footprints>
      <fields>
        <field name="Reference">J</field>
        <field name="Value">CONN_01X02</field>
      </fields>
      <pins>
        <pin num="1" name="P1" type="passive"/>
        <pin num="2" name="P2" type="passive"/>
      </pins>
    </libpart>
    <libpart lib="vfo-do-rescue" part="CONN_01X04">
      <footprints>
        <fp>Pin_Header_Straight_1X*</fp>
        <fp>Pin_Header_Angled_1X*</fp>
        <fp>Socket_Strip_Straight_1X*</fp>
        <fp>Socket_Strip_Angled_1X*</fp>
      </footprints>
      <fields>
        <field name="Reference">J</field>
        <field name="Value">CONN_01X04</field>
      </fields>
      <pins>
        <pin num="1" name="P1" type="passive"/>
        <pin num="2" name="P2" type="passive"/>
        <pin num="3" name="P3" type="passive"/>
        <pin num="4" name="P4" type="passive"/>
      </pins>
    </libpart>
    <libpart lib="vfo-do-rescue" part="CONN_01X07">
      <footprints>
        <fp>Pin_Header_Straight_1X*</fp>
        <fp>Pin_Header_Angled_1X*</fp>
        <fp>Socket_Strip_Straight_1X*</fp>
        <fp>Socket_Strip_Angled_1X*</fp>
      </footprints>
      <fields>
        <field name="Reference">J</field>
        <field name="Value">CONN_01X07</field>
      </fields>
      <pins>
        <pin num="1" name="P1" type="passive"/>
        <pin num="2" name="P2" type="passive"/>
        <pin num="3" name="P3" type="passive"/>
        <pin num="4" name="P4" type="passive"/>
        <pin num="5" name="P5" type="passive"/>
        <pin num="6" name="P6" type="passive"/>
        <pin num="7" name="P7" type="passive"/>
      </pins>
    </libpart>
    <libpart lib="vfo-do-rescue" part="CP_Small">
      <footprints>
        <fp>CP_*</fp>
      </footprints>
      <fields>
        <field name="Reference">C</field>
        <field name="Value">CP_Small</field>
      </fields>
      <pins>
        <pin num="1" name="~" type="passive"/>
        <pin num="2" name="~" type="passive"/>
      </pins>
    </libpart>
    <libpart lib="vfo-do-rescue" part="D_Schottky">
      <footprints>
        <fp>TO-???*</fp>
        <fp>*SingleDiode</fp>
        <fp>*_Diode_*</fp>
        <fp>*SingleDiode*</fp>
        <fp>D_*</fp>
      </footprints>
      <fields>
        <field name="Reference">D</field>
        <field name="Value">D_Schottky</field>
      </fields>
      <pins>
        <pin num="1" name="K" type="passive"/>
        <pin num="2" name="A" type="passive"/>
      </pins>
    </libpart>
  </libparts>
  <libraries>
    <library logical="Memory_EEPROM">
      <uri>/usr/share/kicad/library/Memory_EEPROM.lib</uri>
    </library>
    <library logical="Regulator_Linear">
      <uri>/usr/share/kicad/library/Regulator_Linear.lib</uri>
    </library>
    <library logical="vfo-do-rescue">
      <uri>/home/alkann/Ham/Projets/VFO-DO/vfo-do-rescue.lib</uri>
    </library>
  </libraries>
  <nets>
    <net code="1" name="Net-(P7-Pad1)">
      <node ref="U4" pin="7"/>
      <node ref="P7" pin="1"/>
    </net>
    <net code="2" name="GND">
      <node ref="C4" pin="2"/>
      <node ref="U4" pin="19"/>
      <node ref="C7" pin="1"/>
      <node ref="U6" pin="2"/>
      <node ref="C5" pin="2"/>
      <node ref="P3" pin="2"/>
      <node ref="U3" pin="2"/>
      <node ref="U5" pin="2"/>
      <node ref="P5" pin="4"/>
      <node ref="P4" pin="4"/>
      <node ref="P1" pin="1"/>
      <node ref="U4" pin="14"/>
      <node ref="C1" pin="2"/>
      <node ref="C2" pin="2"/>
      <node ref="C6" pin="2"/>
      <node ref="C3" pin="1"/>
      <node ref="C10" pin="2"/>
      <node ref="C9" pin="2"/>
      <node ref="P8" pin="2"/>
      <node ref="U2" pin="2"/>
      <node ref="P7" pin="2"/>
      <node ref="P6" pin="2"/>
      <node ref="P2" pin="2"/>
      <node ref="U1" pin="2"/>
    </net>
    <net code="3" name="Net-(P6-Pad1)">
      <node ref="P6" pin="1"/>
      <node ref="U4" pin="5"/>
    </net>
    <net code="4" name="Net-(P2-Pad1)">
      <node ref="P2" pin="1"/>
      <node ref="U4" pin="4"/>
    </net>
    <net code="5" name="Net-(U4-Pad3)">
      <node ref="U4" pin="3"/>
    </net>
    <net code="6" name="Net-(U4-Pad6)">
      <node ref="U4" pin="6"/>
    </net>
    <net code="7" name="Net-(U4-Pad10)">
      <node ref="U4" pin="10"/>
    </net>
    <net code="8" name="Net-(P8-Pad1)">
      <node ref="U4" pin="13"/>
      <node ref="P8" pin="1"/>
    </net>
    <net code="9" name="+12V">
      <node ref="P1" pin="2"/>
      <node ref="D1" pin="2"/>
    </net>
    <net code="10" name="Net-(P4-Pad3)">
      <node ref="P4" pin="3"/>
      <node ref="U4" pin="21"/>
    </net>
    <net code="11" name="Net-(C5-Pad1)">
      <node ref="U4" pin="12"/>
      <node ref="C5" pin="1"/>
    </net>
    <net code="12" name="Net-(P3-Pad3)">
      <node ref="P3" pin="3"/>
      <node ref="U1" pin="3"/>
      <node ref="U4" pin="8"/>
    </net>
    <net code="13" name="Net-(U1-Pad5)">
      <node ref="U1" pin="5"/>
    </net>
    <net code="14" name="Net-(P3-Pad5)">
      <node ref="P3" pin="5"/>
    </net>
    <net code="15" name="Net-(P3-Pad6)">
      <node ref="P3" pin="6"/>
    </net>
    <net code="16" name="Net-(P3-Pad7)">
      <node ref="U4" pin="23"/>
      <node ref="P3" pin="7"/>
    </net>
    <net code="17" name="Net-(P3-Pad4)">
      <node ref="U4" pin="9"/>
      <node ref="P3" pin="4"/>
      <node ref="U1" pin="1"/>
    </net>
    <net code="18" name="Net-(C10-Pad1)">
      <node ref="C10" pin="1"/>
      <node ref="U1" pin="4"/>
      <node ref="U3" pin="3"/>
    </net>
    <net code="19" name="Net-(C2-Pad1)">
      <node ref="U6" pin="1"/>
      <node ref="C4" pin="1"/>
      <node ref="C2" pin="1"/>
      <node ref="U2" pin="3"/>
      <node ref="U4" pin="15"/>
      <node ref="U3" pin="1"/>
      <node ref="U5" pin="1"/>
    </net>
    <net code="20" name="Net-(C3-Pad2)">
      <node ref="C3" pin="2"/>
      <node ref="C9" pin="1"/>
      <node ref="U5" pin="3"/>
      <node ref="P3" pin="1"/>
    </net>
    <net code="21" name="Net-(P5-Pad3)">
      <node ref="P5" pin="3"/>
      <node ref="U4" pin="17"/>
    </net>
    <net code="22" name="Net-(P4-Pad2)">
      <node ref="U4" pin="22"/>
      <node ref="P4" pin="2"/>
    </net>
    <net code="23" name="Net-(P4-Pad1)">
      <node ref="P4" pin="1"/>
      <node ref="U4" pin="24"/>
    </net>
    <net code="24" name="Net-(P5-Pad2)">
      <node ref="P5" pin="2"/>
      <node ref="U4" pin="20"/>
    </net>
    <net code="25" name="Net-(U4-Pad1)">
      <node ref="U4" pin="1"/>
    </net>
    <net code="26" name="Net-(U4-Pad11)">
      <node ref="U4" pin="11"/>
    </net>
    <net code="27" name="Net-(U4-Pad16)">
      <node ref="U4" pin="16"/>
    </net>
    <net code="28" name="Net-(U4-Pad18)">
      <node ref="U4" pin="18"/>
    </net>
    <net code="29" name="Net-(U4-Pad2)">
      <node ref="U4" pin="2"/>
    </net>
    <net code="30" name="Net-(U4-Pad25)">
      <node ref="U4" pin="25"/>
    </net>
    <net code="31" name="Net-(U4-Pad26)">
      <node ref="U4" pin="26"/>
    </net>
    <net code="32" name="Net-(U4-Pad27)">
      <node ref="U4" pin="27"/>
    </net>
    <net code="33" name="Net-(U4-Pad28)">
      <node ref="U4" pin="28"/>
    </net>
    <net code="34" name="Net-(U4-Pad29)">
      <node ref="U4" pin="29"/>
    </net>
    <net code="35" name="Net-(U4-Pad30)">
      <node ref="U4" pin="30"/>
    </net>
    <net code="36" name="Net-(C6-Pad1)">
      <node ref="U6" pin="3"/>
      <node ref="P5" pin="1"/>
      <node ref="C6" pin="1"/>
      <node ref="C7" pin="2"/>
    </net>
    <net code="37" name="Net-(C1-Pad1)">
      <node ref="C1" pin="1"/>
      <node ref="U2" pin="1"/>
      <node ref="D1" pin="1"/>
    </net>
  </nets>
</export>
